{
    "scenarioId": "fetch-settlement-reports",
    "scenarioName": "Fetch Settlement Reports",
    "steps": [
        {
            "id": "fetch-settlement-reports",
            "name": "Fetch Settlement Reports",
            "description": "Fetch Settlement Reports",
            "order": 1,
            "method": "GET",
            "endpoint": "partners/{{partnerId}}/merchants/{{merchantId}}/reports",
            "guidePath": "/carbon/additional-operations/fetch-settlement-reports",
            "payload": {},
            "specifications": {
                "reqParams": [],
                "resParams": [
                    {
                        "name": "status",
                        "type": "string",
                        "description": "Status of the request, indicated as either 'SUCCESS' or 'ERROR'."
                    },
                    {
                        "name": "data",
                        "type": "array",
                        "description": "Response data",
                        "resParams": [
                            {
                                "name": "payoutId",
                                "type": "String",
                                "description": "The payout ID used to identify a specific payout."
                            },
                            {
                                "name": "merchantId",
                                "type": "String",
                                "description": "The merchant ID of the merchant for which the settlement report is generated."
                            },
                            {
                                "name": "transactionStartDate",
                                "type": "String",
                                "description": "The date of the first transaction in the generated settlement report, in YYYY-MM-DD format."
                            },
                            {
                                "name": "transactionEndDate",
                                "type": "String",
                                "description": "The date of the last transaction in the generated settlement report, in YYYY-MM-DD format."
                            },
                            {
                                "name": "settlementDate",
                                "type": "String",
                                "description": "Date of the payout, in YYYY-MM-DD format."
                            },
                            {
                                "name": "reportType",
                                "type": "String",
                                "description": "Specifies the type of settlement report opted for the merchant. It can be either 'MONTHLY' or 'DAILY’."
                            },
                            {
                                "name": "url",
                                "type": "String",
                                "description": "URL from which the particular settlement report can be viewed."
                            },
                            {
                                "name": "totalSale",
                                "type": "Number",
                                "description": "The total amount of sales generated by the merchant during the report period."
                            },
                            {
                                "name": "totalRefund",
                                "type": "Number",
                                "description": "The total amount refunded by the merchant during the specified time period."
                            },
                            {
                                "name": "fee",
                                "type": "Number",
                                "description": "The total fee collected from transactions during the settlement."
                            },
                            {
                                "name": "payout",
                                "type": "Number",
                                "description": "The final amount paid out to the merchant after all deductions."
                            }
                        ]
                    },
                    {
                        "name": "message",
                        "type": "string",
                        "description": "A message that describes the status of the request."
                    }
                ]
            }
        }
    ]
}
